geefetch/__init__.py
geefetch/__main__.py
geefetch/py.typed
geefetch/cli/__init__.py
geefetch/cli/debug.py
geefetch/cli/download_implementation.py
geefetch/cli/logging_implementation.py
geefetch/cli/main.py
geefetch/cli/omegaconfig.py
geefetch/data/__init__.py
geefetch/data/get.py
geefetch/data/process.py
geefetch/data/tiler.py
geefetch/data/downloadables/__init__.py
geefetch/data/downloadables/abc.py
geefetch/data/downloadables/collection.py
geefetch/data/downloadables/geedim.py
geefetch/data/downloadables/image.py
geefetch/data/satellites/__init__.py
geefetch/data/satellites/abc.py
geefetch/data/satellites/custom.py
geefetch/data/satellites/dem.py
geefetch/data/satellites/dynworld.py
geefetch/data/satellites/gedi.py
geefetch/data/satellites/landsat8.py
geefetch/data/satellites/palsar2.py
geefetch/data/satellites/s1.py
geefetch/data/satellites/s2.py
geefetch/utils/__init__.py
geefetch/utils/config.py
geefetch/utils/enums.py
geefetch/utils/gee.py
geefetch/utils/geedim.py
geefetch/utils/geopandas.py
geefetch/utils/log.py
geefetch/utils/log_multiprocessing.py
geefetch/utils/path.py
geefetch/utils/progress.py
geefetch/utils/progress_multiprocessing.py
geefetch/utils/rasterio.py
geefetch-0.6.0.dist-info/entry_points.txt
geefetch-0.6.0.dist-info/licenses/LICENSE
geefetch-0.6.0.dist-info/WHEEL
geefetch-0.6.0.dist-info/METADATA
geefetch-0.6.0.dist-info/RECORD
