Metadata-Version: 2.4
Name: geefetch
Version: 0.6.0
Summary: A Python library/CLI to download large scale satellite data from Google Earth Engine.
Author-email: Gabriel Belouze <gabriel@belouze.com>
Requires-Python: >=3.10
Classifier: Development Status :: 2 - Pre-Alpha
Classifier: Intended Audience :: Developers
Classifier: License :: OSI Approved :: MIT License
Classifier: Operating System :: OS Independent
Classifier: Programming Language :: Python
Classifier: Programming Language :: Python :: 3
Classifier: Programming Language :: Python :: 3.10
Classifier: Programming Language :: Python :: 3.11
License-File: LICENSE
Requires-Dist: click>=8.2.0
Requires-Dist: earthengine-api
Requires-Dist: gee_s1_processing
Requires-Dist: geedim<2.0.0
Requires-Dist: geobbox>=0.1.0
Requires-Dist: geopandas>=1.0.1
Requires-Dist: jsons
Requires-Dist: numpy
Requires-Dist: omegaconf
Requires-Dist: pooch
Requires-Dist: pyarrow
Requires-Dist: rasterio>=1.3
Requires-Dist: retry
Requires-Dist: rich
Requires-Dist: shapely>=2.0.6
Requires-Dist: thefuzz
Requires-Dist: dotenv ; extra == "dev"
Requires-Dist: mypy ; extra == "dev"
Requires-Dist: pre-commit ; extra == "dev"
Requires-Dist: pydoclint[flake8] ; extra == "dev"
Requires-Dist: pytest ; extra == "dev"
Requires-Dist: ruff ; extra == "dev"
Requires-Dist: types-requests ; extra == "dev"
Requires-Dist: types-retry ; extra == "dev"
Requires-Dist: mkdocs-git-revision-date-localized-plugin>=1.4.1 ; extra == "doc"
Requires-Dist: mkdocs-include-markdown-plugin>=7.1.5 ; extra == "doc"
Requires-Dist: mkdocs-material>=9.6.7 ; extra == "doc"
Requires-Dist: mkdocs>=1.6.1 ; extra == "doc"
Requires-Dist: mkdocstrings-python>=1.16.2 ; extra == "doc"
Requires-Dist: mkdocstrings>=0.28.2 ; extra == "doc"
Project-URL: source, https://github.com/gbelouze/geefetch
Project-URL: tracker, https://github.com/gbelouze/geefetch/issues
Provides-Extra: dev
Provides-Extra: doc
